CB2325NumericaG3/__init__.py
CB2325NumericaG3/aproximacao.py
CB2325NumericaG3/erros.py
CB2325NumericaG3/integracao.py
CB2325NumericaG3/interpolacao.py
CB2325NumericaG3/raizes.py
CB2325NumericaG3/soma_de_kahan.py
CB2325NumericaG3/visualizacao_raizes.py
cb2325numericag3-0.0.2.dist-info/licenses/LICENSE
cb2325numericag3-0.0.2.dist-info/WHEEL
cb2325numericag3-0.0.2.dist-info/METADATA
cb2325numericag3-0.0.2.dist-info/RECORD
