Metadata-Version: 2.4
Name: CB2325NumericaG3
Version: 0.0.2
Summary: Biblioteca de cálculo numérico
Author-email: Anizio Silva <al.anizio.junior@impatech.edu.br>, Cristiane Magarinos <al.cristiane.sampaio@impatech.edu.br>, Davi Bezerra <al.davi.guimaraes@impatech.edu.br>, Felipe Lima <al.felipe.sousa@impatech.edu.br>, Felipe Ribeiro <al.felipe.mendonca@impatech.edu.br>, Gabriel Falcão <al.gabriel.martinez@impatech.edu.br>, Guilherme Oséias <al.guilherme.silva@impatech.edu.br>, Heitor Ramos <al.heitor.pereira@impatech.edu.br>, João Pedro Lima <al.joao.almeida@impatech.edu.br>, Natália Brandão <
Requires-Python: >=3.8
License-File: LICENSE
Requires-Dist: matplotlib
Requires-Dist: numpy
Project-URL: Homepage, https://github.com/al-gabriel-martinez/CB2325NumericaG3
